lightex/__init__.py
lightex/config_base.py
lightex/assets/__init__.py
lightex/assets/lxconfig.py
lightex/assets/run_expts.py
lightex/dispatch/__init__.py
lightex/dispatch/config_containers.py
lightex/dispatch/config_engines.py
lightex/dispatch/dispatch.py
lightex/dispatch/docker_utils.py
lightex/dispatch/k8sutils.py
lightex/dispatch/process_utils.py
lightex/mulogger/__init__.py
lightex/mulogger/abstract_logger.py
lightex/mulogger/config.py
lightex/mulogger/multi_logger.py
lightex/mulogger/trains_logger.py
lightex/mulogger/wandb_logger.py
lightex/namedconf/__init__.py
lightex/namedconf/config_utils.py
lightex/namedconf/replace_utils.py
lightex/qviz/__init__.py
lightex/qviz/show.py
lightex-0.0.5.2.data/scripts/lx
lightex-0.0.5.2.dist-info/LICENSE
lightex-0.0.5.2.dist-info/METADATA
lightex-0.0.5.2.dist-info/WHEEL
lightex-0.0.5.2.dist-info/top_level.txt
lightex-0.0.5.2.dist-info/RECORD
