Metadata-Version: 2.1
Name: lightex
Version: 0.0.5.2
Summary: LightEx: A Light Experiment Manager
Home-page: https://github.com/ofnote/lightex
Author: Nishant Sinha
Author-email: nishant@offnote.co
License: Apache 2.0
Platform: POSIX
Classifier: Environment :: Console
Classifier: Intended Audience :: Developers
Classifier: License :: OSI Approved :: Apache Software License
Classifier: Operating System :: OS Independent
Classifier: Programming Language :: Python :: 3.7
Classifier: Topic :: Software Development
Classifier: Topic :: Scientific/Engineering :: Artificial Intelligence
Requires-Python: >3.6.0
Requires-Dist: easydict
Requires-Dist: dacite
Requires-Dist: kubernetes
Requires-Dist: docker
Requires-Dist: dataclasses ; python_version < "3.7"
